{
  "trigger": true,
  "modules": [
    "verification-link"
  ],
  "parentResource": "ehailingapp2cf216052cf21605",
  "functionName": "ehailingapp2cf216052cf21605CustomMessage",
  "resourceName": "ehailingapp2cf216052cf21605CustomMessage",
  "parentStack": "auth",
  "triggerEnvs": [
    {
      "key": "RESOURCENAME",
      "value": "resourceName"
    }
  ],
  "triggerDir": "C:\\snapshot\\repo\\build\\node_modules\\@aws-amplify\\amplify-category-auth\\provider-utils\\awscloudformation\\triggers\\CustomMessage",
  "triggerTemplate": "CustomMessage.json.ejs",
  "triggerEventPath": "CustomMessage.event.json",
  "roleName": "ehailingapp2cf216052cf21605CustomMessage",
  "skipEdit": true,
  "REDIRECTURL": "",
  "EMAILSUBJECT": "",
  "EMAILMESSAGE": "",
  "RESOURCENAME": "resourceName",
  "enableCors": false
}